{
  "source_file": "report3.txt",
  "category": "ozel",
  "chunk_index": 169,
  "chunk_text": "Bu proje kapsamında belirtilen kurallar dizilerinin kurgulanması ve hatalı bir defter üretmenin risklerinden kurtulmak ve berat iptalinin zorlukları ile uğraşmamak için, defterlerin hatasız bir şekilde oluşturulması sağlanacaktır. Planlanan diğer önemli bir faliyet ise kurgulanacak yapının günümüz finansal ve muhasebesel süreçleri tabanında Sayfa 37 / 74 oluşacak olan değişikliklere hızlı şekilde adapte olma esnekliğine sahip olacak şekilde tasarlanacak olmasıdır.",
  "char_len": 468,
  "sentence_count": 2
}