{
  "source_file": "report3.txt",
  "category": "genel",
  "chunk_index": 157,
  "chunk_text": "Yine aynı kurumların hukuk birimleri, mevzuattaki değişiklikleri farklı kaynaklardan takip etmekte, risk ve uyum takibini yapan ekipleri bilgilendirmektedir. Bu bilgilendirme ile birlikte risk ve uyum takibini sağlayan ekipler, ilgili mevzuat değişikliklerinin takip edilen risk ve uyumlar ile ilgisi olup olmadığını tesbit etmekte ve riskin giderilmesi/uyumun sağlanabilmesi amacıyla hangi aksiyonları alacaklarını risk/uyum ile ilgili birimler yardımıyla belirlemektedirler. Sonrasında yine dağıtık kaynaklardan (aksiyon alması gereken her birimden) bilgileri toplamakta ve aksiyon durumlarını, dolayısıyla risk/uyum statülerini belirleyip raporlamaktadırlar. Buradaki temel ihtiyaç, dağıtık olarak bilgi toplayan/veri girişi yapan tüm birimlerin, olası otomasyon ve entegrasyonlar yapılarak, tek bir platform üzerinde veri girişi, takip ve raporlama yapabilmeleridir. Proje Proje kapsamında öncelikli olarak kuruluşumuzun mevcut faaliyetleri, benzer uygulamalar ve müşteri talepleri Kapsamında de dikkate alınarak mevcut sistem ve veri yapıları hakkında bilgiler toplanacaktır.Proje kapsamında yer alacak Yapılacak olan modüller ve özetle fonksiyonaliteleri aşağıdaki gibi olacaktır; - Uyum Evreni Modülü Kurumun, mevcut Faaliyetler mevzuata olan uyumunun kontrol edildiği modüldür.",
  "char_len": 1285,
  "sentence_count": 5
}