{
  "source_file": "report3.txt",
  "category": "genel",
  "chunk_index": 127,
  "chunk_text": "Burada dilbilimi açısından destek alınabilir ya da hazır doğal dil işleme API leri kullanılabilir. - Bu kelimeler benzerliklerine göre varsayılan olarak belli sınıflara bağlanacaktır. İlk etapta elle yapılacak müdahale ile bu varsayımlar düzeltilecektir. - Sistem bundan sonraki yeni ihale verilerinde, mevcut sınıflandırılmış verileri de göz önünde bulundurarak olması gereken sınıflandırmayı yeni kelimeler için sağlayacaktır. - Bundan sonraki adımda daha önce sınıflandırılmamış kelimeler Naive Bayes gibi olasılık hesaplayan algoritmalarla, birlikte kullanıldıkları daha önceden sınıflandırılmış kelimelerle en yakın olasılığı kullanarak aynı sınıflandırmaya tabi tutulacaklar. - Sistem buradaki kendi başarı oranını hesaplayarak, kullanıcılardan bazen destek isteyecektir. Örneğin, sınıflandırılmış kelimelerle birlikte kullanılan kelimeler aynı yoğunlukta kullanılmıyorsa –belli oran altında ise- kullanıcıdan teyit isteyebilecektir. Örneğin; mukavva kelimesi, Ambalaj ile mi ilgilidir, Kağıt/Selüloz ile mi, yoksa ikisi içinde mi? - Kelime yoğunluklarının ya da bilgi açısından değerlerinin belirlenebilmesi için kullanılabilecek yöntemler ile alakalı akademik ya da profesyonel destek alınacaktır. - Bu karar mekanizmasının hızlı çalışabilmesi için gerekli teknik altyapı oluşturulmalıdır. Kararsız kalındığı noktada, kullanıcıdan geri dönüş hızlıca alınabilmelidir. - Bu hızı sağlayabilmek için sürekli girdi çıktı sağlayan hızlı bir teknik altyapı oluşturulacaktır.",
  "char_len": 1475,
  "sentence_count": 5
}