{
  "source_file": "report2.txt",
  "category": "genel",
  "chunk_index": 98,
  "chunk_text": "İkincil olarak tekrarlı satın alım yapılacak ürünlerin stok seviyeleri de kritik bir ihtiyaçtır. Doğru zamanda doğru stok seviyesini tutarak firmalar stok tutma maliyetleri ile stok eksikliğinden müşteri ve satış kaybından oluşacak zararı dengelemeleri gerekmektedir. Stok optimizasyonu alanında piyasada bulunan ürün ve servisler tekrarlı satın alım ve e-ticaretin spesifik sektörlerine göre özelleşmiş ve optimize edilmiş durumda değillerdir. Bu sistemler aynı zamanda çok fazla veriye ihtiyaç duymakta ve günümüzde e-ticaretin çok hızlı değişen envanterlerine ayak uyduramamaktadırlar. Özellikle projenin hedef aldığı sektörlerde e-ticaret sitesinin envanterinin %50’den fazlası 6 aydan kısa bir süre içinde değişebilmekte ve ortalama bir ürünün satışta kaldığı süreler de 3 ayın altında inebilmektedir.",
  "char_len": 806,
  "sentence_count": 5
}