{
  "source_file": "report2.txt",
  "category": "genel",
  "chunk_index": 141,
  "chunk_text": "Bu entegrasyonlar içinde hem ülkemizde hem de dünyada kısıtlı miktarda sunulabilen tekil bir müşterinin bütün kanallar üzerinde tekilleştirilmesi ve ona sunulan kişiselleştirilmiş alışveriş deneyiminin gerçek zamanlı devamlılığının sağlanabilmesi önem taşımaktadır. Bu projenin bir diğer amacı da proje kapsamında verilen platformlar için bu tekilleştirme ve öneri sistemlerinin bütünleştirilmesini (omni-channel personalization) sağlamaktır. Sayfa 40 / 66 Proje Seçilen platformlar için analizler uygulanacak ve her bir platform için geliştirilecek ara-katman çözümünün sunacağı kabiliyet setleri Kapsamında analistlerimiz tarafından ortaya konulacaktır. Şirket dışından alınan danışmanlık hizmeti ile analiz son haline getirilecek ve yazılım Yapılacak geliştirme ekibi için teknik gereksinimlere dönüştürülecektir. Daha sonra yazılım geliştirme ekibi çıkarılan kabiliyetlere uygun şekilde Faaliyetler yazılımı geliştirecek ve her bir platformun kendi pazarlama alanında sunulması için satış ve pazarlama ekiplerine aktarılacaktır.",
  "char_len": 1032,
  "sentence_count": 5
}