{
  "source_file": "report3.txt",
  "category": "mevzuat",
  "chunk_index": 142,
  "chunk_text": "Bankacılık sektöründe işletme riskini azaltacak, riski derecelendirecek ve kârlılık analizi yapılmasını sağlayacak olan verinin fazla miktarda bulunmaması ve eldeki yöntemler içerisinde çok zor elde edilebilmesi ve bu konuda sadece kredibilite bilgisinin alınabilmesi belirli alanlarda yetersiz kalmaktadır. Proje Bu kapsamda kredibilite bilgisinin yanında firma onayı ile ilgili analizler yapılarak güvenilir değişken oranı Kapsamında hesaplanacaktır. E-defter süreçlerindeki tüm finansal hareketler izlenip findexten alınan kredibilite ile birlikte Yapılacak bu oran hesaplanacaktır. E-defter tarafındaki bakılacak finansal muhasebesel parametreler kapsamında Faaliyetler buradan alacağımız güven oranı, yapacağımız araştırmalar ve konu ile ilgili danışmanlık hizmetleri sonrasında şekillenecektir. Uygulama geliştirme aşamasında kullanılacak araçların hızlı bir şekilde değiştirilebilmesi ve güncel teknolojilere hızlıca adapte olunabilmesi için yüksek ölçüde otomasyonlaştırılmış Public/Private Cloud’a geçilmesi hedeflenmektedir. Süreç işleme aşamalarındaki karar mekanizmalarının hızlı çalışabilmesi için gerekli teknik altyapı oluşturulmalıdır.",
  "char_len": 1151,
  "sentence_count": 6
}